[
{ "en": "economic", "ja": "経済の" },
{ "en": "economy", "ja": "経済" },
{ "en": "edit", "ja": "編集する" },
{ "en": "educate", "ja": "教育する" },
{ "en": "effective", "ja": "効果的な" },
{ "en": "efficient", "ja": "効率的な" },
{ "en": "elaborate", "ja": "精巧な" },
{ "en": "eliminate", "ja": "排除する" },
{ "en": "elite", "ja": "精鋭" },
{ "en": "embody", "ja": "体現する" },
{ "en": "emerge", "ja": "出現する" },
{ "en": "emission", "ja": "排出" },
{ "en": "emphasis", "ja": "強調" },
{ "en": "empirical", "ja": "実証的な" },
{ "en": "enable", "ja": "可能にする" },
{ "en": "encounter", "ja": "遭遇する" },
{ "en": "encourage", "ja": "促す" },
{ "en": "endure", "ja": "耐える" },
{ "en": "enforce", "ja": "施行する" },
{ "en": "enhance", "ja": "強化する" },
{ "en": "enormous", "ja": "莫大な" },
{ "en": "ensure", "ja": "確保する" },
{ "en": "entity", "ja": "実体" },
{ "en": "environment", "ja": "環境" },
{ "en": "epidemic", "ja": "流行" },
{ "en": "equality", "ja": "平等" },
{ "en": "equation", "ja": "方程式" },
{ "en": "equilibrium", "ja": "均衡" },
{ "en": "equip", "ja": "装備する" },
{ "en": "equivalent", "ja": "同等の" },
{ "en": "era", "ja": "時代" },
{ "en": "erosion", "ja": "侵食" },
{ "en": "essential", "ja": "不可欠な" },
{ "en": "establish", "ja": "確立する" },
{ "en": "estimate", "ja": "推定する" },
{ "en": "ethic", "ja": "倫理" },
{ "en": "evaluate", "ja": "評価する" },
{ "en": "evidence", "ja": "証拠" },
{ "en": "evolution", "ja": "進化" },
{ "en": "exceed", "ja": "超える" },
{ "en": "exclude", "ja": "除外する" },
{ "en": "execute", "ja": "実行する" },
{ "en": "exhibit", "ja": "展示する" },
{ "en": "expand", "ja": "拡大する" },
{ "en": "expenditure", "ja": "支出" },
{ "en": "experiment", "ja": "実験" },
{ "en": "expertise", "ja": "専門知識" },
{ "en": "explicit", "ja": "明示的な" },
{ "en": "exploit", "ja": "利用する" },
{ "en": "explore", "ja": "探究する" },
{ "en": "export", "ja": "輸出" },
{ "en": "expose", "ja": "暴露する" },
{ "en": "external", "ja": "外部の" }
]